kcfetcher/__init__.py
kcfetcher/main.py
kcfetcher/data/kcfetcher_blacklist
kcfetcher/fetch/__init__.py
kcfetcher/fetch/client.py
kcfetcher/fetch/client_registration_policies.py
kcfetcher/fetch/client_scope.py
kcfetcher/fetch/component.py
kcfetcher/fetch/custom_authentication.py
kcfetcher/fetch/factory.py
kcfetcher/fetch/generic.py
kcfetcher/fetch/group.py
kcfetcher/fetch/identity_provider.py
kcfetcher/fetch/realm.py
kcfetcher/fetch/role.py
kcfetcher/fetch/user.py
kcfetcher/fetch/user_federation.py
kcfetcher/store/__init__.py
kcfetcher/store/store.py
kcfetcher/utils/__init__.py
kcfetcher/utils/helper.py
keycloak_fetch_bot-0.0.9.dist-info/METADATA
keycloak_fetch_bot-0.0.9.dist-info/WHEEL
keycloak_fetch_bot-0.0.9.dist-info/entry_points.txt
keycloak_fetch_bot-0.0.9.dist-info/top_level.txt
keycloak_fetch_bot-0.0.9.dist-info/RECORD
