Metadata-Version: 2.1
Name: keycloak-fetch-bot
Version: 0.0.9
Summary: Export data from KeyCloak server
Author: Cesar Valdez
Project-URL: repository, https://github.com/cesarvr/keycloak-fetch-bot
Keywords: KeyCloak
Requires-Python: >=3.8
Requires-Dist: kcapi (>=1.0.39)
Requires-Dist: importlib-resources
